mapscript/__init__.py
mapscript/_mapscript.pyd
mapscript/mapscript.py
mapscript/examples/__init__.py
mapscript/examples/project_csv.py
mapscript/examples/shpdump.py
mapscript/examples/shpinfo.py
mapscript/examples/wxs.py
mapscript/tests/__init__.py
mapscript/tests/class_test.py
mapscript/tests/clone_test.py
mapscript/tests/cluster_test.py
mapscript/tests/color_test.py
mapscript/tests/config_test.py
mapscript/tests/font_test.py
mapscript/tests/hash_test.py
mapscript/tests/image_test.py
mapscript/tests/label_test.py
mapscript/tests/layer_test.py
mapscript/tests/line_test.py
mapscript/tests/map_test.py
mapscript/tests/outputformat_test.py
mapscript/tests/ows_test.py
mapscript/tests/parentreference_test.py
mapscript/tests/pgtest.py
mapscript/tests/point_test.py
mapscript/tests/rect_test.py
mapscript/tests/refcount_test.py
mapscript/tests/resultcache_test.py
mapscript/tests/shape_test.py
mapscript/tests/shapefile_test.py
mapscript/tests/style_test.py
mapscript/tests/symbol_test.py
mapscript/tests/symbolset_test.py
mapscript/tests/testing.py
mapscript/tests/thread_test.py
mapscript/tests/zoom_test.py
mapscript/tests/data/cities.csv
mapscript/tests/data/fonts.txt
mapscript/tests/data/home.png
mapscript/tests/data/line.dbf
mapscript/tests/data/line.shp
mapscript/tests/data/line.shx
mapscript/tests/data/mapserver-sample.conf
mapscript/tests/data/point.dbf
mapscript/tests/data/point.shp
mapscript/tests/data/point.shx
mapscript/tests/data/polygon.dbf
mapscript/tests/data/polygon.shp
mapscript/tests/data/polygon.shx
mapscript/tests/data/raster.tfw
mapscript/tests/data/raster.tif
mapscript/tests/data/symbols.txt
mapscript/tests/data/test.map
mapscript/tests/data/test.png
mapscript/tests/data/test_nofontset.map
mapscript/tests/data/xmarks.png
mapscript/tests/data/vera/COPYRIGHT.TXT
mapscript/tests/data/vera/README.TXT
mapscript/tests/data/vera/RELEASENOTES.TXT
mapscript/tests/data/vera/Vera.ttf
mapscript/tests/data/vera/VeraBd.ttf
mapscript-8.6.0.dist-info/METADATA
mapscript-8.6.0.dist-info/WHEEL
mapscript-8.6.0.dist-info/top_level.txt
mapscript-8.6.0.dist-info/RECORD
